ising_animate/__init__.py
ising_animate/__main__.py
ising_animate/ising.py
ising_animate/lattice.py
ising_animate/timer.py
ising_animate/examples/__init__.py
ising_animate/examples/dynamic.py
ising_animate/examples/heating.py
ising_animate-0.0.2.dist-info/LICENSE
ising_animate-0.0.2.dist-info/METADATA
ising_animate-0.0.2.dist-info/WHEEL
ising_animate-0.0.2.dist-info/top_level.txt
ising_animate-0.0.2.dist-info/RECORD
