Metadata-Version: 2.1
Name: ising-animate
Version: 0.0.2
Summary: A module to easily generate animations of the Ising Model
Home-page: https://github.com/davifeliciano/ising_model
Author: Davi Feliciano
Author-email: dfeliciano37@gmail.com
License: UNKNOWN
Project-URL: Bug Tracker, https://github.com/davi_feliciano/ising_model/issues
Project-URL: Documentation, https://davifeliciano.github.io/ising_animate/index.html
Platform: UNKNOWN
Classifier: Programming Language :: Python :: 3
Classifier: License :: OSI Approved :: MIT License
Classifier: Operating System :: OS Independent
Classifier: Intended Audience :: Education
Classifier: Intended Audience :: Science/Research
Classifier: Topic :: Scientific/Engineering :: Mathematics
Classifier: Topic :: Scientific/Engineering :: Physics
Classifier: Topic :: Scientific/Engineering :: Visualization
Requires-Python: >=3.6
License-File: LICENSE
Requires-Dist: arrow
Requires-Dist: matplotlib
Requires-Dist: numpy
Requires-Dist: progressbar2
